blueprint/__init__.py
blueprint/assets.py
blueprint/models.py
blueprint/service.py
blueprint/util.py
blueprint/validation.py
blueprint/gateway/__init__.py
blueprint/gateway/validators.py
bluprnt-0.2.6.dist-info/LICENSE
bluprnt-0.2.6.dist-info/METADATA
bluprnt-0.2.6.dist-info/WHEEL
bluprnt-0.2.6.dist-info/top_level.txt
bluprnt-0.2.6.dist-info/RECORD
