Metadata-Version: 2.1
Name: bluprnt
Version: 0.2.6
Summary: A small helper package for Blueprint project.
Home-page: UNKNOWN
Author: Chris Wacker
Author-email: chriswacker228@gmail.com
License: UNKNOWN
Platform: UNKNOWN
Classifier: Programming Language :: Python :: 3
Classifier: License :: OSI Approved :: MIT License
Classifier: Operating System :: OS Independent
Requires-Python: >=3.7
Requires-Dist: requests
